acmecse/__init__.py
acmecse/__main__.py
acmecse/onboarding.py
acmecse/databases/DBBinding.py
acmecse/databases/PostgreSQLBinding.py
acmecse/databases/TinyDBBinding.py
acmecse/databases/__init__.py
acmecse/etc/ACMEUtils.py
acmecse/etc/Constants.py
acmecse/etc/DateUtils.py
acmecse/etc/GeoTools.py
acmecse/etc/IDUtils.py
acmecse/etc/RequestUtils.py
acmecse/etc/ResponseStatusCodes.py
acmecse/etc/Types.py
acmecse/etc/Utils.py
acmecse/etc/__init__.py
acmecse/helpers/ACMEIntEnum.py
acmecse/helpers/ACMELRUCache.py
acmecse/helpers/BackgroundWorker.py
acmecse/helpers/CoAPthonTools.py
acmecse/helpers/EventManager.py
acmecse/helpers/Interpreter.py
acmecse/helpers/KeyHandler.py
acmecse/helpers/MQTTConnection.py
acmecse/helpers/MultiDict.py
acmecse/helpers/NetworkTools.py
acmecse/helpers/OAuth.py
acmecse/helpers/OrderedSet.py
acmecse/helpers/PerfTimer.py
acmecse/helpers/ReadWriteLock.py
acmecse/helpers/ResourceSemaphore.py
acmecse/helpers/TextTools.py
acmecse/helpers/ThreadSafeCounter.py
acmecse/helpers/TinyDBBetterTable.py
acmecse/helpers/TinyDBBufferedStorage.py
acmecse/helpers/__init__.py
acmecse/init/ASFunctions.as
acmecse/init/acme.ini.default
acmecse/init/agd-dev.fcp
acmecse/init/agd-mc.fcp
acmecse/init/attributePolicies.ap
acmecse/init/attributePolicies.fcp
acmecse/init/cid-dev.fcp
acmecse/init/cod-dev.fcp
acmecse/init/cod-mc.fcp
acmecse/init/cod-sdev.fcp
acmecse/init/complexTypePolicies.ap
acmecse/init/configurations.docmd
acmecse/init/enumTypesPolicies.ep
acmecse/init/hed-dev.fcp
acmecse/init/hed-mc.fcp
acmecse/init/hed-sdev.fcp
acmecse/init/hod-dev.fcp
acmecse/init/hod-mc.fcp
acmecse/init/ind-dev.fcp
acmecse/init/ind-mc.fcp
acmecse/init/init.as
acmecse/init/mad-dev.fcp
acmecse/init/mad-mc.fcp
acmecse/init/mad-sdev.fcp
acmecse/init/mdd-mc.fcp
acmecse/init/rad-dev.fcp
acmecse/init/rad-mc.fcp
acmecse/init/ved-dev.fcp
acmecse/init/ved-mc.fcp
acmecse/init/demoDocumentationTutorials/hacksterIO.as
acmecse/init/demoDocumentationTutorials/init.as
acmecse-2025.3.2.dist-info/LICENSE
acmecse-2025.3.2.dist-info/METADATA
acmecse-2025.3.2.dist-info/WHEEL
acmecse-2025.3.2.dist-info/entry_points.txt
acmecse-2025.3.2.dist-info/top_level.txt
acmecse-2025.3.2.dist-info/RECORD
