Metadata-Version: 2.2
Name: acmecse
Version: 2025.3.2
Summary: An open source CSE Middleware for Education
Home-page: https://acmecse.net
Author: Andreas Kraft
Author-email: an.kraft@gmail.com
License: BSD
Classifier: License :: OSI Approved :: BSD License
Classifier: Programming Language :: Python :: 3.10
License-File: LICENSE
Requires-Dist: cachetools
Requires-Dist: coapthon3-acme-cse
Requires-Dist: cbor2
Requires-Dist: flask
Requires-Dist: flask-cors
Requires-Dist: InquirerPy
Requires-Dist: isodate
Requires-Dist: paho-mqtt>=2.0.0
Requires-Dist: plotext
Requires-Dist: psycopg2-binary
Requires-Dist: pyperclip
Requires-Dist: rdflib
Requires-Dist: requests
Requires-Dist: rich
Requires-Dist: shapely
Requires-Dist: textual==1.0.0
Requires-Dist: textual-plotext>=1.0.0
Requires-Dist: tinydb
Requires-Dist: waitress
Requires-Dist: websockets
Dynamic: author
Dynamic: author-email
Dynamic: classifier
Dynamic: description
Dynamic: description-content-type
Dynamic: home-page
Dynamic: license
Dynamic: requires-dist
Dynamic: summary
